customcircle/__init__.py
customcircle/generator.py
customcircle-0.1.0.dist-info/METADATA
customcircle-0.1.0.dist-info/WHEEL
customcircle-0.1.0.dist-info/top_level.txt
customcircle-0.1.0.dist-info/RECORD
