Metadata-Version: 2.4
Name: customcircle
Version: 0.1.0
Summary: Generate a circle image with a user's name inside
Author-email: Prateek <prateekact17@gmail.com>
License: MIT
Requires-Python: >=3.7
Requires-Dist: Pillow
